{
  "name": "TableDataProvider",
  "selector": null,
  "kind": "Class",
  "sourceFile": "table-data-provider.ts",
  "sourceLine": 334,
  "sourceUrl": "https://github.com/SAP/fundamental-ngx/blob/9318050/libs/platform/table-helpers/domain/table-data-provider.ts#L334",
  "description": "",
  "inputs": [],
  "outputs": [],
  "methods": [
    {
      "name": "fetch",
      "signature": "(tableState?: TableState) => Observable<T[]>",
      "description": "Method for retrieving the data.",
      "deprecated": null,
      "sourceLine": 341,
      "since": null,
      "parameters": [
        {
          "name": "tableState",
          "type": "TableState",
          "description": "",
          "optional": true
        }
      ],
      "returnType": "Observable<T[]>"
    },
    {
      "name": "fetchData",
      "signature": "(state: TableState) => Observable<T[]>",
      "description": "Method for applying filtering and retrieving the data.",
      "deprecated": null,
      "sourceLine": 350,
      "since": null,
      "parameters": [
        {
          "name": "state",
          "type": "TableState",
          "description": "",
          "optional": false
        }
      ],
      "returnType": "Observable<T[]>"
    },
    {
      "name": "getFieldOptions",
      "signature": "(field: string) => Observable<SelectItem<any>[]>",
      "description": "Method for getting all possible options for particular field.\nUsed for creating select options.\nDevelopers can override this method to extend the filtering functionality.",
      "deprecated": null,
      "sourceLine": 374,
      "since": null,
      "parameters": [
        {
          "name": "field",
          "type": "string",
          "description": "key of the data item.",
          "optional": false
        }
      ],
      "returnType": "Observable<SelectItem<any>[]>"
    }
  ],
  "inherited": {
    "from": "BaseTableDataProvider",
    "inputs": [],
    "methods": [
      {
        "name": "applyFiltering",
        "signature": "(items: T[], filters: CollectionFilterAndGroup[]) => T[]",
        "description": "Method for filtering the data.",
        "deprecated": null,
        "sourceLine": 58,
        "since": null,
        "parameters": [
          {
            "name": "items",
            "type": "T[]",
            "description": "Array of data source items.",
            "optional": false
          },
          {
            "name": "filters",
            "type": "CollectionFilterAndGroup[]",
            "description": "Set of column filters.",
            "optional": false
          }
        ],
        "returnType": "T[]"
      },
      {
        "name": "collectionFilterGroupStrategy",
        "signature": "(item: T, filter: CollectionFilterGroup) => boolean",
        "description": "Method which applies group filtering conditions for the item.",
        "deprecated": null,
        "sourceLine": 125,
        "since": null,
        "parameters": [
          {
            "name": "item",
            "type": "T",
            "description": "Item to apply conditions to.",
            "optional": false
          },
          {
            "name": "filter",
            "type": "CollectionFilterGroup",
            "description": "Filter group.",
            "optional": false
          }
        ],
        "returnType": "boolean"
      },
      {
        "name": "collectionFilterStrategy",
        "signature": "(item: T, filter: CollectionFilter) => boolean",
        "description": "Method which filters item depending on applied condition result.\nDevelopers can override this method to extend its functionality",
        "deprecated": null,
        "sourceLine": 94,
        "since": null,
        "parameters": [
          {
            "name": "item",
            "type": "T",
            "description": "Item to apply conditions to.",
            "optional": false
          },
          {
            "name": "filter",
            "type": "CollectionFilter",
            "description": "Column filter.",
            "optional": false
          }
        ],
        "returnType": "boolean"
      },
      {
        "name": "getFilteringStrategy",
        "signature": "(item: T, filters: CollectionFilterAndGroup[]) => boolean",
        "description": "Method which selects appropriate filtering strategy of the field depending on the filter type.\nDevelopers can override this method to extend the filtering functionality.",
        "deprecated": null,
        "sourceLine": 75,
        "since": null,
        "parameters": [
          {
            "name": "item",
            "type": "T",
            "description": "item of the data source.",
            "optional": false
          },
          {
            "name": "filters",
            "type": "CollectionFilterAndGroup[]",
            "description": "Set of column filters.",
            "optional": false
          }
        ],
        "returnType": "boolean"
      },
      {
        "name": "search",
        "signature": "(items: T[], tableState: TableState) => T[]",
        "description": "Applies search of the search term for visible table columns.\nDevelopers can override this method to extend the filtering functionality.",
        "deprecated": null,
        "sourceLine": 138,
        "since": null,
        "parameters": [
          {
            "name": "items",
            "type": "T[]",
            "description": "data source items array.",
            "optional": false
          },
          {
            "name": "tableState",
            "type": "TableState",
            "description": "",
            "optional": false
          }
        ],
        "returnType": "T[]"
      },
      {
        "name": "setFilters",
        "signature": "(filterBy: CollectionFilterAndGroup[], searchInput?: SearchInput) => void",
        "description": "Method for setting external filtering conditions.",
        "deprecated": null,
        "sourceLine": 47,
        "since": null,
        "parameters": [
          {
            "name": "filterBy",
            "type": "CollectionFilterAndGroup[]",
            "description": "Set of column filters.",
            "optional": false
          },
          {
            "name": "searchInput",
            "type": "SearchInput",
            "description": "Search condition from search field.",
            "optional": true
          }
        ],
        "returnType": "void"
      }
    ]
  }
}