{
  "name": "DialogBodyComponent",
  "selector": "fd-dialog-body",
  "kind": "Component",
  "sourceFile": "dialog-body.component.ts",
  "sourceLine": 54,
  "sourceUrl": "https://github.com/SAP/fundamental-ngx/blob/38469d8/libs/core/dialog/dialog-body/dialog-body.component.ts#L54",
  "description": "Applies fundamental layout and styling to the contents of a dialog body.\n\n```html\n<fd-dialog-body>\n    <!-- Content -->\n</fd-dialog-body>\n```",
  "inputs": [
    {
      "name": "disablePaddings",
      "type": "boolean",
      "default": null,
      "description": "property to remove the horizontal and vertical paddings from the body\ndefault is set to false",
      "isSignal": true,
      "deprecated": null,
      "sourceLine": 59,
      "since": null
    }
  ],
  "outputs": [],
  "methods": [],
  "inherited": null
}