{
  "name": "ListFocusItem",
  "selector": null,
  "kind": "Class",
  "sourceFile": "list-focus-item.model.ts",
  "sourceLine": 7,
  "sourceUrl": "https://github.com/SAP/fundamental-ngx/blob/be0ae12/libs/core/list/list-focus-item.model.ts#L7",
  "description": "",
  "inputs": [
    {
      "name": "value",
      "type": "T",
      "default": null,
      "description": "Value of the list item.\nUsed for dropdown-based controls such as combobox, select, etc.",
      "isSignal": false,
      "deprecated": null,
      "sourceLine": 21,
      "since": null
    }
  ],
  "outputs": [],
  "methods": [],
  "inherited": null
}